{
  "exportInfo": {
    "type": "full_backup",
    "theme": "default",
    "version": "2.0",
    "exportedAt": "2025-10-17 01:17:43"
  },
  "user": {
    "_id": "68e75576e51d5965971ba085",
    "name": "kashish sharma",
    "email": "kashishsharma9977@gmail.com",
    "currency": "INR",
    "monthlyBudget": 0,
    "createdAt": "2025-10-09T06:25:58.938Z",
    "updatedAt": "2025-10-12T07:27:13.740Z",
    "__v": 0
  },
  "data": {
    "expenses": [
      {
        "_id": "68f13980fecd82e89c8d2e7f",
        "amount": 500,
        "description": "fee",
        "category": {
          "_id": "68e759aa25afc3293d0c6ac3",
          "name": "Bills & Utilities",
          "type": "expense",
          "color": "#84CC16"
        },
        "date": "2025-11-16",
        "type": "expense",
        "user": "68e75576e51d5965971ba085",
        "tags": [],
        "createdAt": "2025-10-16T18:29:20.633Z",
        "updatedAt": "2025-10-16T18:29:20.633Z",
        "__v": 0
      },
      {
        "_id": "68e7b4bf32073199fc905897",
        "amount": 10,
        "description": "just fun",
        "category": {
          "_id": "68e759b125afc3293d0c6ac8",
          "name": "Entertainment",
          "type": "expense",
          "color": "#EC4899"
        },
        "date": "2025-10-14",
        "type": "expense",
        "user": "68e75576e51d5965971ba085",
        "tags": [],
        "createdAt": "2025-10-09T13:12:31.456Z",
        "updatedAt": "2025-10-09T13:21:28.812Z",
        "__v": 0
      },
      {
        "_id": "68e75aa625afc3293d0c6bcc",
        "amount": 3000,
        "description": "Clothes Shopping",
        "category": {
          "_id": "68e7599f25afc3293d0c6abe",
          "name": "Shopping",
          "type": "expense",
          "color": "#8B5CF6"
        },
        "date": "2025-10-11",
        "type": "expense",
        "user": "68e75576e51d5965971ba085",
        "tags": [],
        "createdAt": "2025-10-09T06:48:06.232Z",
        "updatedAt": "2025-10-09T06:58:24.009Z",
        "__v": 0
      },
      {
        "_id": "68ea1b95a5be8ebe3a65b779",
        "amount": 500,
        "description": "Clothes Shopping",
        "category": {
          "_id": "68e7599f25afc3293d0c6abe",
          "name": "Shopping",
          "type": "expense",
          "color": "#8B5CF6"
        },
        "date": "2025-10-11",
        "type": "expense",
        "user": "68e75576e51d5965971ba085",
        "tags": [],
        "createdAt": "2025-10-11T08:55:49.483Z",
        "updatedAt": "2025-10-11T08:55:49.483Z",
        "__v": 0
      },
      {
        "_id": "68e75aba25afc3293d0c6bda",
        "amount": 1000,
        "description": "Movie & Dinner",
        "category": {
          "_id": "68e759b125afc3293d0c6ac8",
          "name": "Entertainment",
          "type": "expense",
          "color": "#EC4899"
        },
        "date": "2025-10-10",
        "type": "expense",
        "user": "68e75576e51d5965971ba085",
        "tags": [],
        "createdAt": "2025-10-09T06:48:26.585Z",
        "updatedAt": "2025-10-09T06:53:08.832Z",
        "__v": 0
      },
      {
        "_id": "68e7aa82f6ffc8f572dc3a47",
        "amount": 5000,
        "description": "Create website",
        "category": {
          "_id": "68e759d525afc3293d0c6ad7",
          "name": "Freelance",
          "type": "income",
          "color": "#3B82F6"
        },
        "date": "2025-10-10",
        "type": "income",
        "user": "68e75576e51d5965971ba085",
        "tags": [],
        "createdAt": "2025-10-09T12:28:50.422Z",
        "updatedAt": "2025-10-09T12:28:50.422Z",
        "__v": 0
      },
      {
        "_id": "68e75a1825afc3293d0c6b30",
        "amount": 50000,
        "description": "Monthly Salary",
        "category": {
          "_id": "68e759c025afc3293d0c6acd",
          "name": "Salary",
          "type": "income",
          "color": "#10B981"
        },
        "date": "2025-10-09",
        "type": "income",
        "user": "68e75576e51d5965971ba085",
        "tags": [],
        "createdAt": "2025-10-09T06:45:44.002Z",
        "updatedAt": "2025-10-09T06:45:44.002Z",
        "__v": 0
      },
      {
        "_id": "68e75a2925afc3293d0c6b3e",
        "amount": 15000,
        "description": "Freelance Project",
        "category": {
          "_id": "68e759d525afc3293d0c6ad7",
          "name": "Freelance",
          "type": "income",
          "color": "#3B82F6"
        },
        "date": "2025-10-09",
        "type": "income",
        "user": "68e75576e51d5965971ba085",
        "tags": [],
        "createdAt": "2025-10-09T06:46:01.911Z",
        "updatedAt": "2025-10-09T06:46:01.911Z",
        "__v": 0
      },
      {
        "_id": "68e75a3c25afc3293d0c6b4c",
        "amount": 10000,
        "description": "Performance Bonus",
        "category": {
          "_id": "68e759e825afc3293d0c6adc",
          "name": "Bonus",
          "type": "income",
          "color": "#F97316"
        },
        "date": "2025-10-09",
        "type": "income",
        "user": "68e75576e51d5965971ba085",
        "tags": [],
        "createdAt": "2025-10-09T06:46:20.933Z",
        "updatedAt": "2025-10-09T06:46:20.933Z",
        "__v": 0
      },
      {
        "_id": "68e75a4c25afc3293d0c6b5a",
        "amount": 5000,
        "description": "Grocery Shopping",
        "category": {
          "_id": "68e7599025afc3293d0c6ab4",
          "name": "Food & Dining",
          "type": "expense",
          "color": "#EF4444"
        },
        "date": "2025-10-09",
        "type": "expense",
        "user": "68e75576e51d5965971ba085",
        "tags": [],
        "createdAt": "2025-10-09T06:46:36.666Z",
        "updatedAt": "2025-10-09T06:46:36.666Z",
        "__v": 0
      },
      {
        "_id": "68e75a8125afc3293d0c6bb0",
        "amount": 2000,
        "description": "Electricity Bill",
        "category": {
          "_id": "68e759aa25afc3293d0c6ac3",
          "name": "Bills & Utilities",
          "type": "expense",
          "color": "#84CC16"
        },
        "date": "2025-10-09",
        "type": "expense",
        "user": "68e75576e51d5965971ba085",
        "tags": [],
        "createdAt": "2025-10-09T06:47:29.603Z",
        "updatedAt": "2025-10-09T06:47:29.603Z",
        "__v": 0
      },
      {
        "_id": "68e75a9025afc3293d0c6bbe",
        "amount": 1500,
        "description": "Uber Rides",
        "category": {
          "_id": "68e7599925afc3293d0c6ab9",
          "name": "Transportation",
          "type": "expense",
          "color": "#3B82F6"
        },
        "date": "2025-10-09",
        "type": "expense",
        "user": "68e75576e51d5965971ba085",
        "tags": [],
        "createdAt": "2025-10-09T06:47:44.749Z",
        "updatedAt": "2025-10-09T06:53:13.171Z",
        "__v": 0
      }
    ],
    "categories": [
      {
        "_id": "68e7599025afc3293d0c6ab4",
        "name": "Food & Dining",
        "type": "expense",
        "color": "#EF4444",
        "icon": "receipt",
        "user": "68e75576e51d5965971ba085",
        "createdAt": "2025-10-09T06:43:28.563Z",
        "updatedAt": "2025-10-09T06:43:28.563Z",
        "__v": 0
      },
      {
        "_id": "68e7599925afc3293d0c6ab9",
        "name": "Transportation",
        "type": "expense",
        "color": "#3B82F6",
        "icon": "receipt",
        "user": "68e75576e51d5965971ba085",
        "createdAt": "2025-10-09T06:43:37.107Z",
        "updatedAt": "2025-10-09T06:43:37.107Z",
        "__v": 0
      },
      {
        "_id": "68e7599f25afc3293d0c6abe",
        "name": "Shopping",
        "type": "expense",
        "color": "#8B5CF6",
        "icon": "receipt",
        "user": "68e75576e51d5965971ba085",
        "createdAt": "2025-10-09T06:43:43.514Z",
        "updatedAt": "2025-10-09T06:43:43.514Z",
        "__v": 0
      },
      {
        "_id": "68e759aa25afc3293d0c6ac3",
        "name": "Bills & Utilities",
        "type": "expense",
        "color": "#84CC16",
        "icon": "receipt",
        "user": "68e75576e51d5965971ba085",
        "createdAt": "2025-10-09T06:43:54.794Z",
        "updatedAt": "2025-10-09T06:44:21.107Z",
        "__v": 0
      },
      {
        "_id": "68e759b125afc3293d0c6ac8",
        "name": "Entertainment",
        "type": "expense",
        "color": "#EC4899",
        "icon": "receipt",
        "user": "68e75576e51d5965971ba085",
        "createdAt": "2025-10-09T06:44:01.082Z",
        "updatedAt": "2025-10-09T06:44:01.082Z",
        "__v": 0
      },
      {
        "_id": "68e759c025afc3293d0c6acd",
        "name": "Salary",
        "type": "income",
        "color": "#10B981",
        "icon": "receipt",
        "user": "68e75576e51d5965971ba085",
        "createdAt": "2025-10-09T06:44:16.889Z",
        "updatedAt": "2025-10-09T06:44:16.889Z",
        "__v": 0
      },
      {
        "_id": "68e759d525afc3293d0c6ad7",
        "name": "Freelance",
        "type": "income",
        "color": "#3B82F6",
        "icon": "receipt",
        "user": "68e75576e51d5965971ba085",
        "createdAt": "2025-10-09T06:44:37.339Z",
        "updatedAt": "2025-10-09T06:44:37.339Z",
        "__v": 0
      },
      {
        "_id": "68e759e825afc3293d0c6adc",
        "name": "Bonus",
        "type": "income",
        "color": "#F97316",
        "icon": "receipt",
        "user": "68e75576e51d5965971ba085",
        "createdAt": "2025-10-09T06:44:56.251Z",
        "updatedAt": "2025-10-09T06:44:56.251Z",
        "__v": 0
      }
    ],
    "budgets": [
      {
        "_id": "68e75b8251dcb403a0ab1d27",
        "category": {
          "_id": "68e7599025afc3293d0c6ab4",
          "name": "Food & Dining",
          "type": "expense",
          "color": "#EF4444"
        },
        "amount": 10000,
        "month": 10,
        "year": 2025,
        "user": "68e75576e51d5965971ba085",
        "createdAt": "2025-10-09 12:21:46",
        "updatedAt": "2025-10-09 12:21:46",
        "__v": 0
      },
      {
        "_id": "68e75b8e51dcb403a0ab1d34",
        "category": {
          "_id": "68e7599925afc3293d0c6ab9",
          "name": "Transportation",
          "type": "expense",
          "color": "#3B82F6"
        },
        "amount": 5000,
        "month": 10,
        "year": 2025,
        "user": "68e75576e51d5965971ba085",
        "createdAt": "2025-10-09 12:21:58",
        "updatedAt": "2025-10-09 12:21:58",
        "__v": 0
      },
      {
        "_id": "68e75b9a51dcb403a0ab1d41",
        "category": {
          "_id": "68e7599f25afc3293d0c6abe",
          "name": "Shopping",
          "type": "expense",
          "color": "#8B5CF6"
        },
        "amount": 8000,
        "month": 10,
        "year": 2025,
        "user": "68e75576e51d5965971ba085",
        "createdAt": "2025-10-09 12:22:10",
        "updatedAt": "2025-10-09 12:22:10",
        "__v": 0
      },
      {
        "_id": "68e75ba351dcb403a0ab1d4e",
        "category": {
          "_id": "68e759aa25afc3293d0c6ac3",
          "name": "Bills & Utilities",
          "type": "expense",
          "color": "#84CC16"
        },
        "amount": 3000,
        "month": 10,
        "year": 2025,
        "user": "68e75576e51d5965971ba085",
        "createdAt": "2025-10-09 12:22:19",
        "updatedAt": "2025-10-09 12:22:19",
        "__v": 0
      },
      {
        "_id": "68e75bb051dcb403a0ab1d5b",
        "category": {
          "_id": "68e759b125afc3293d0c6ac8",
          "name": "Entertainment",
          "type": "expense",
          "color": "#EC4899"
        },
        "amount": 4000,
        "month": 10,
        "year": 2025,
        "user": "68e75576e51d5965971ba085",
        "createdAt": "2025-10-09 12:22:32",
        "updatedAt": "2025-10-09 12:22:32",
        "__v": 0
      }
    ]
  },
  "statistics": {
    "totalExpenses": 12,
    "totalCategories": 8,
    "totalBudgets": 5,
    "totalIncome": 80000,
    "totalSpending": 13510,
    "dateRange": {
      "oldestRecord": "2025-10-09",
      "newestRecord": "2025-11-16"
    }
  }
}